examples/example-chisel3/test_run_dir/gcd.GCDTester906586546/GCD.v
`ifdef RANDOMIZE_GARBAGE_ASSIGN
`define RANDOMIZE
`endif
`ifdef RANDOMIZE_INVALID_ASSIGN
`define RANDOMIZE
`endif
`ifdef RANDOMIZE_REG_INIT
`define RANDOMIZE
`endif
`ifdef RANDOMIZE_MEM_INIT
`define RANDOMIZE
`endif

module GCD(
  input         clock,
  input         reset,
  input  [15:0] io_value1,
  input  [15:0] io_value2,
  input         io_loadingValues,
  output [15:0] io_outputGCD,
  output        io_outputValid
);
  reg [15:0] x; // @[GCD.scala 21:15]
  reg [31:0] _RAND_0;
  reg [15:0] y; // @[GCD.scala 22:15]
  reg [31:0] _RAND_1;
  wire  _T_9; // @[GCD.scala 24:10]
  wire [16:0] _T_10; // @[GCD.scala 24:24]
  wire [16:0] _T_11; // @[GCD.scala 24:24]
  wire [15:0] _T_12; // @[GCD.scala 24:24]
  wire [16:0] _T_13; // @[GCD.scala 25:25]
  wire [16:0] _T_14; // @[GCD.scala 25:25]
  wire [15:0] _T_15; // @[GCD.scala 25:25]
  wire [15:0] _GEN_0; // @[GCD.scala 24:15]
  wire [15:0] _GEN_1; // @[GCD.scala 24:15]
  wire [15:0] _GEN_2; // @[GCD.scala 27:26]
  wire [15:0] _GEN_3; // @[GCD.scala 27:26]
  wire  _T_17; // @[GCD.scala 33:23]
  assign _T_9 = x > y; // @[GCD.scala 24:10]
  assign _T_10 = x - y; // @[GCD.scala 24:24]
  assign _T_11 = $unsigned(_T_10); // @[GCD.scala 24:24]
  assign _T_12 = _T_11[15:0]; // @[GCD.scala 24:24]
  assign _T_13 = y - x; // @[GCD.scala 25:25]
  assign _T_14 = $unsigned(_T_13); // @[GCD.scala 25:25]
  assign _T_15 = _T_14[15:0]; // @[GCD.scala 25:25]
  assign _GEN_0 = _T_9 ? _T_12 : x; // @[GCD.scala 24:15]
  assign _GEN_1 = _T_9 ? y : _T_15; // @[GCD.scala 24:15]
  assign _GEN_2 = io_loadingValues ? io_value1 : _GEN_0; // @[GCD.scala 27:26]
  assign _GEN_3 = io_loadingValues ? io_value2 : _GEN_1; // @[GCD.scala 27:26]
  assign _T_17 = y == 16'h0; // @[GCD.scala 33:23]
  assign io_outputGCD = x;
  assign io_outputValid = _T_17;
`ifdef RANDOMIZE
  integer initvar;
  initial begin
    `ifndef verilator
      #0.002 begin end
    `endif
  `ifdef RANDOMIZE_REG_INIT
  _RAND_0 = {1{$random}};
  x = _RAND_0[15:0];
  `endif // RANDOMIZE_REG_INIT
  `ifdef RANDOMIZE_REG_INIT
  _RAND_1 = {1{$random}};
  y = _RAND_1[15:0];
  `endif // RANDOMIZE_REG_INIT
  end
`endif // RANDOMIZE
  always @(posedge clock) begin
    if (io_loadingValues) begin
      x <= io_value1;
    end else begin
      if (_T_9) begin
        x <= _T_12;
      end
    end
    if (io_loadingValues) begin
      y <= io_value2;
    end else begin
      if (!(_T_9)) begin
        y <= _T_15;
      end
    end
  end
endmodule

examples/example-chisel3/test_run_dir/gcd.GCDTester271644267/GCD.vcd
$date
2018-07-11T13:00+0000
$end
$version
0.2
$end
$comment

$end
$timescale 1ps  $end
$scope module GCD $end
 $var wire 16 ! io_outputGCD $end
 $var wire 1 " io_outputValid $end
 $var wire 16 # y $end
 $var wire 16 $ io_value2 $end
 $var wire 1 % clock $end
 $var wire 16 & x $end
 $var wire 16 ' io_value1 $end
 $var wire 1 ( reset $end
 $var wire 1 ) io_loadingValues $end
$upscope $end
$enddefinitions $end
$dumpvars
0%
0"
1(
b1110111010000000 #
1)
b0101001111000100 $
b0111110011001111 !
b1111000101101101 '
b0111110011001111 &
$end
#1
b0101001111000100 #
1%
b1111000101101101 &
b1111000101101101 !
#2
0%
#3
1%
#4
0%
#5
1%
#6
0%
#7
1%
#8
0%
#9
1%
#10
b0000000000000001 '
0%
0(
b0000000000000001 $
#11
1%
b0000000000000001 !
b0000000000000001 &
b0000000000000001 #
#12
0)
0%
#13
1%
b0000000000000000 #
1"
#14
b0000000000001000 $
0%
1)
#15
1%
0"
b0000000000001000 #
#16
0)
0%
#17
1%
b0000000000000111 #
#18
0%
#19
1%
b0000000000000110 #
#20
0%
#21
b0000000000000101 #
1%
#22
0%
#23
b0000000000000100 #
1%
#24
0%
#25
1%
b0000000000000011 #
#26
0%
#27
b0000000000000010 #
1%
#28
0%
#29
1%
b0000000000000001 #
#30
0%
#31
1%
b0000000000000000 #
1"
#32
b0000000000001111 $
0%
1)
#33
1%
0"
b0000000000001111 #
#34
0)
0%
#35
b0000000000001110 #
1%
#36
0%
#37
1%
b0000000000001101 #
#38
0%
#39
1%
b0000000000001100 #
#40
0%
#41
1%
b0000000000001011 #
#42
0%
#43
1%
b0000000000001010 #
#44
0%
#45
b0000000000001001 #
1%
#46
0%
#47
1%
b0000000000001000 #
#48
0%
#49
1%
b0000000000000111 #
#50
0%
#51
1%
b0000000000000110 #
#52
0%
#53
b0000000000000101 #
1%
#54
0%
#55
b0000000000000100 #
1%
#56
0%
#57
1%
b0000000000000011 #
#58
0%
#59
b0000000000000010 #
1%
#60
0%
#61
1%
b0000000000000001 #
#62
0%
#63
1%
b0000000000000000 #
1"
#64
b0000000000010110 $
0%
1)
#65
b0000000000010110 #
1%
0"
#66
0)
0%
#67
1%
b0000000000010101 #
#68
0%
#69
1%
b0000000000010100 #
#70
0%
#71
1%
b0000000000010011 #
#72
0%
#73
1%
b0000000000010010 #
#74
0%
#75
1%
b0000000000010001 #
#76
0%
#77
b0000000000010000 #
1%
#78
0%
#79
1%
b0000000000001111 #
#80
0%
#81
b0000000000001110 #
1%
#82
0%
#83
1%
b0000000000001101 #
#84
0%
#85
1%
b0000000000001100 #
#86
0%
#87
1%
b0000000000001011 #
#88
0%
#89
1%
b0000000000001010 #
#90
0%
#91
b0000000000001001 #
1%
#92
0%
#93
1%
b0000000000001000 #
#94
0%
#95
1%
b0000000000000111 #
#96
0%
#97
1%
b0000000000000110 #
#98
0%
#99
b0000000000000101 #
1%
#100
0%
#101
b0000000000000100 #
1%
#102
0%
#103
1%
b0000000000000011 #
#104
0%
#105
b0000000000000010 #
1%
#106
0%
#107
1%
b0000000000000001 #
#108
0%
#109
1%
b0000000000000000 #
1"
#110
0%
b0000000000011101 $
1)
#111
b0000000000011101 #
1%
0"
#112
0)
0%
#113
1%
b0000000000011100 #
#114
0%
#115
b0000000000011011 #
1%
#116
0%
#117
1%
b0000000000011010 #
#118
0%
#119
1%
b0000000000011001 #
#120
0%
#121
b0000000000011000 #
1%
#122
0%
#123
1%
b0000000000010111 #
#124
0%
#125
b0000000000010110 #
1%
#126
0%
#127
1%
b0000000000010101 #
#128
0%
#129
1%
b0000000000010100 #
#130
0%
#131
1%
b0000000000010011 #
#132
0%
#133
1%
b0000000000010010 #
#134
0%
#135
1%
b0000000000010001 #
#136
0%
#137
b0000000000010000 #
1%
#138
0%
#139
1%
b0000000000001111 #
#140
0%
#141
b0000000000001110 #
1%
#142
0%
#143
1%
b0000000000001101 #
#144
0%
#145
1%
b0000000000001100 #
#146
0%
#147
1%
b0000000000001011 #
#148
0%
#149
1%
b0000000000001010 #
#150
0%
#151
b0000000000001001 #
1%
#152
0%
#153
1%
b0000000000001000 #
#154
0%
#155
1%
b0000000000000111 #
#156
0%
#157
1%
b0000000000000110 #
#158
0%
#159
b0000000000000101 #
1%
#160
0%
#161
b0000000000000100 #
1%
#162
0%
#163
1%
b0000000000000011 #
#164
0%
#165
b0000000000000010 #
1%
#166
0%
#167
1%
b0000000000000001 #
#168
0%
#169
1%
b0000000000000000 #
1"
#170
0%
1)
b0000000000100100 $
#171
1%
0"
b0000000000100100 #
#172
0)
0%
#173
1%
b0000000000100011 #
#174
0%
#175
b0000000000100010 #
1%
#176
0%
#177
1%
b0000000000100001 #
#178
0%
#179
1%
b0000000000100000 #
#180
0%
#181
b0000000000011111 #
1%
#182
0%
#183
1%
b0000000000011110 #
#184
0%
#185
b0000000000011101 #
1%
#186
0%
#187
1%
b0000000000011100 #
#188
0%
#189
b0000000000011011 #
1%
#190
0%
#191
1%
b0000000000011010 #
#192
0%
#193
1%
b0000000000011001 #
#194
0%
#195
b0000000000011000 #
1%
#196
0%
#197
1%
b0000000000010111 #
#198
0%
#199
b0000000000010110 #
1%
#200
0%
#201
1%
b0000000000010101 #
#202
0%
#203
1%
b0000000000010100 #
#204
0%
#205
1%
b0000000000010011 #
#206
0%
#207
1%
b0000000000010010 #
#208
0%
#209
1%
b0000000000010001 #
#210
0%
#211
b0000000000010000 #
1%
#212
0%
#213
1%
b0000000000001111 #
#214
0%
#215
b0000000000001110 #
1%
#216
0%
#217
1%
b0000000000001101 #
#218
0%
#219
1%
b0000000000001100 #
#220
0%
#221
1%
b0000000000001011 #
#222
0%
#223
1%
b0000000000001010 #
#224
0%
#225
b0000000000001001 #
1%
#226
0%
#227
1%
b0000000000001000 #
#228
0%
#229
1%
b0000000000000111 #
#230
0%
#231
1%
b0000000000000110 #
#232
0%
#233
b0000000000000101 #
1%
#234
0%
#235
b0000000000000100 #
1%
#236
0%
#237
1%
b0000000000000011 #
#238
0%
#239
b0000000000000010 #
1%
#240
0%
#241
1%
b0000000000000001 #
#242
0%
#243
1%
b0000000000000000 #
1"
#244
0%
1)
b0000000000000001 $
b0000000000000100 '
#245
1%
0"
b0000000000000100 &
b0000000000000100 !
b0000000000000001 #
#246
0)
0%
#247
1%
b0000000000000011 &
b0000000000000011 !
#248
0%
#249
b0000000000000010 &
1%
b0000000000000010 !
#250
0%
#251
1%
b0000000000000001 !
b0000000000000001 &
#252
0%
#253
1%
b0000000000000000 #
1"
#254
b0000000000001000 $
0%
1)
#255
1%
0"
b0000000000000100 &
b0000000000000100 !
b0000000000001000 #
#256
0)
0%
#257
b0000000000000100 #
1%
#258
0%
#259
1%
b0000000000000000 #
1"
#260
b0000000000001111 $
0%
1)
#261
1%
0"
b0000000000001111 #
#262
0)
0%
#263
1%
b0000000000001011 #
#264
0%
#265
1%
b0000000000000111 #
#266
0%
#267
1%
b0000000000000011 #
#268
0%
#269
1%
b0000000000000001 !
b0000000000000001 &
#270
0%
#271
b0000000000000010 #
1%
#272
0%
#273
1%
b0000000000000001 #
#274
0%
#275
1%
b0000000000000000 #
1"
#276
b0000000000010110 $
0%
1)
#277
b0000000000010110 #
1%
0"
b0000000000000100 &
b0000000000000100 !
#278
0)
0%
#279
1%
b0000000000010010 #
#280
0%
#281
b0000000000001110 #
1%
#282
0%
#283
1%
b0000000000001010 #
#284
0%
#285
1%
b0000000000000110 #
#286
0%
#287
b0000000000000010 #
1%
#288
0%
#289
b0000000000000010 &
1%
b0000000000000010 !
#290
0%
#291
1%
b0000000000000000 #
1"
#292
0%
b0000000000011101 $
1)
#293
b0000000000011101 #
1%
0"
b0000000000000100 &
b0000000000000100 !
#294
0)
0%
#295
1%
b0000000000011001 #
#296
0%
#297
1%
b0000000000010101 #
#298
0%
#299
1%
b0000000000010001 #
#300
0%
#301
1%
b0000000000001101 #
#302
0%
#303
b0000000000001001 #
1%
#304
0%
#305
b0000000000000101 #
1%
#306
0%
#307
1%
b0000000000000001 #
#308
0%
#309
1%
b0000000000000011 &
b0000000000000011 !
#310
0%
#311
b0000000000000010 &
1%
b0000000000000010 !
#312
0%
#313
1%
b0000000000000001 !
b0000000000000001 &
#314
0%
#315
1%
b0000000000000000 #
1"
#316
0%
1)
b0000000000100100 $
#317
1%
0"
b0000000000000100 &
b0000000000000100 !
b0000000000100100 #
#318
0)
0%
#319
1%
b0000000000100000 #
#320
0%
#321
1%
b0000000000011100 #
#322
0%
#323
b0000000000011000 #
1%
#324
0%
#325
1%
b0000000000010100 #
#326
0%
#327
b0000000000010000 #
1%
#328
0%
#329
1%
b0000000000001100 #
#330
0%
#331
1%
b0000000000001000 #
#332
0%
#333
b0000000000000100 #
1%
#334
0%
#335
1%
b0000000000000000 #
1"
#336
b0000000000000111 '
0%
1)
b0000000000000001 $
#337
b0000000000000111 !
1%
0"
b0000000000000001 #
b0000000000000111 &
#338
0)
0%
#339
b0000000000000110 !
1%
b0000000000000110 &
#340
0%
#341
1%
b0000000000000101 &
b0000000000000101 !
#342
0%
#343
1%
b0000000000000100 &
b0000000000000100 !
#344
0%
#345
1%
b0000000000000011 &
b0000000000000011 !
#346
0%
#347
b0000000000000010 &
1%
b0000000000000010 !
#348
0%
#349
1%
b0000000000000001 !
b0000000000000001 &
#350
0%
#351
1%
b0000000000000000 #
1"
#352
b0000000000001000 $
0%
1)
#353
b0000000000000111 !
1%
0"
b0000000000001000 #
b0000000000000111 &
#354
0)
0%
#355
1%
b0000000000000001 #
#356
0%
#357
b0000000000000110 !
1%
b0000000000000110 &
#358
0%
#359
1%
b0000000000000101 &
b0000000000000101 !
#360
0%
#361
1%
b0000000000000100 &
b0000000000000100 !
#362
0%
#363
1%
b0000000000000011 &
b0000000000000011 !
#364
0%
#365
b0000000000000010 &
1%
b0000000000000010 !
#366
0%
#367
1%
b0000000000000001 !
b0000000000000001 &
#368
0%
#369
1%
b0000000000000000 #
1"
#370
b0000000000001111 $
0%
1)
#371
b0000000000000111 !
1%
0"
b0000000000001111 #
b0000000000000111 &
#372
0)
0%
#373
1%
b0000000000001000 #
#374
0%
#375
1%
b0000000000000001 #
#376
0%
#377
b0000000000000110 !
1%
b0000000000000110 &
#378
0%
#379
1%
b0000000000000101 &
b0000000000000101 !
#380
0%
#381
1%
b0000000000000100 &
b0000000000000100 !
#382
0%
#383
1%
b0000000000000011 &
b0000000000000011 !
#384
0%
#385
b0000000000000010 &
1%
b0000000000000010 !
#386
0%
#387
1%
b0000000000000001 !
b0000000000000001 &
#388
0%
#389
1%
b0000000000000000 #
1"
#390
b0000000000010110 $
0%
1)
#391
b0000000000010110 #
b0000000000000111 !
1%
0"
b0000000000000111 &
#392
0)
0%
#393
1%
b0000000000001111 #
#394
0%
#395
1%
b0000000000001000 #
#396
0%
#397
1%
b0000000000000001 #
#398
0%
#399
b0000000000000110 !
1%
b0000000000000110 &
#400
0%
#401
1%
b0000000000000101 &
b0000000000000101 !
#402
0%
#403
1%
b0000000000000100 &
b0000000000000100 !
#404
0%
#405
1%
b0000000000000011 &
b0000000000000011 !
#406
0%
#407
b0000000000000010 &
1%
b0000000000000010 !
#408
0%
#409
1%
b0000000000000001 !
b0000000000000001 &
#410
0%
#411
1%
b0000000000000000 #
1"
#412
0%
b0000000000011101 $
1)
#413
b0000000000000111 !
b0000000000011101 #
1%
0"
b0000000000000111 &
#414
0)
0%
#415
b0000000000010110 #
1%
#416
0%
#417
1%
b0000000000001111 #
#418
0%
#419
1%
b0000000000001000 #
#420
0%
#421
1%
b0000000000000001 #
#422
0%
#423
b0000000000000110 !
1%
b0000000000000110 &
#424
0%
#425
1%
b0000000000000101 &
b0000000000000101 !
#426
0%
#427
1%
b0000000000000100 &
b0000000000000100 !
#428
0%
#429
1%
b0000000000000011 &
b0000000000000011 !
#430
0%
#431
b0000000000000010 &
1%
b0000000000000010 !
#432
0%
#433
1%
b0000000000000001 !
b0000000000000001 &
#434
0%
#435
1%
b0000000000000000 #
1"
#436
0%
1)
b0000000000100100 $
#437
b0000000000000111 !
1%
0"
b0000000000100100 #
b0000000000000111 &
#438
0)
0%
#439
b0000000000011101 #
1%
#440
0%
#441
b0000000000010110 #
1%
#442
0%
#443
1%
b0000000000001111 #
#444
0%
#445
1%
b0000000000001000 #
#446
0%
#447
1%
b0000000000000001 #
#448
0%
#449
b0000000000000110 !
1%
b0000000000000110 &
#450
0%
#451
1%
b0000000000000101 &
b0000000000000101 !
#452
0%
#453
1%
b0000000000000100 &
b0000000000000100 !
#454
0%
#455
1%
b0000000000000011 &
b0000000000000011 !
#456
0%
#457
b0000000000000010 &
1%
b0000000000000010 !
#458
0%
#459
1%
b0000000000000001 !
b0000000000000001 &
#460
0%
#461
1%
b0000000000000000 #
1"
#462
0%
1)
b0000000000001010 '
b0000000000000001 $
#463
b0000000000001010 !
b0000000000001010 &
1%
0"
b0000000000000001 #
#464
0)
0%
#465
1%
b0000000000001001 &
b0000000000001001 !
#466
0%
#467
1%
b0000000000001000 !
b0000000000001000 &
#468
0%
#469
b0000000000000111 !
1%
b0000000000000111 &
#470
0%
#471
b0000000000000110 !
1%
b0000000000000110 &
#472
0%
#473
1%
b0000000000000101 &
b0000000000000101 !
#474
0%
#475
1%
b0000000000000100 &
b0000000000000100 !
#476
0%
#477
1%
b0000000000000011 &
b0000000000000011 !
#478
0%
#479
b0000000000000010 &
1%
b0000000000000010 !
#480
0%
#481
1%
b0000000000000001 !
b0000000000000001 &
#482
0%
#483
1%
b0000000000000000 #
1"
#484
b0000000000001000 $
0%
1)
#485
b0000000000001010 !
b0000000000001010 &
1%
0"
b0000000000001000 #
#486
0)
0%
#487
b0000000000000010 &
1%
b0000000000000010 !
#488
0%
#489
1%
b0000000000000110 #
#490
0%
#491
b0000000000000100 #
1%
#492
0%
#493
b0000000000000010 #
1%
#494
0%
#495
1%
b0000000000000000 #
1"
#496
b0000000000001111 $
0%
1)
#497
b0000000000001010 !
b0000000000001010 &
1%
0"
b0000000000001111 #
#498
0)
0%
#499
b0000000000000101 #
1%
#500
0%
#501
1%
b0000000000000101 &
b0000000000000101 !
#502
0%
#503
1%
b0000000000000000 #
1"
#504
b0000000000010110 $
0%
1)
#505
b0000000000010110 #
b0000000000001010 !
b0000000000001010 &
1%
0"
#506
0)
0%
#507
1%
b0000000000001100 #
#508
0%
#509
b0000000000000010 #
1%
#510
0%
#511
1%
b0000000000001000 !
b0000000000001000 &
#512
0%
#513
b0000000000000110 !
1%
b0000000000000110 &
#514
0%
#515
1%
b0000000000000100 &
b0000000000000100 !
#516
0%
#517
b0000000000000010 &
1%
b0000000000000010 !
#518
0%
#519
1%
b0000000000000000 #
1"
#520
0%
b0000000000011101 $
1)
#521
b0000000000001010 !
b0000000000011101 #
b0000000000001010 &
1%
0"
#522
0)
0%
#523
1%
b0000000000010011 #
#524
0%
#525
b0000000000001001 #
1%
#526
0%
#527
1%
b0000000000000001 !
b0000000000000001 &
#528
0%
#529
1%
b0000000000001000 #
#530
0%
#531
1%
b0000000000000111 #
#532
0%
#533
1%
b0000000000000110 #
#534
0%
#535
b0000000000000101 #
1%
#536
0%
#537
b0000000000000100 #
1%
#538
0%
#539
1%
b0000000000000011 #
#540
0%
#541
b0000000000000010 #
1%
#542
0%
#543
1%
b0000000000000001 #
#544
0%
#545
1%
b0000000000000000 #
1"
#546
0%
1)
b0000000000100100 $
#547
b0000000000001010 !
b0000000000001010 &
1%
0"
b0000000000100100 #
#548
0)
0%
#549
1%
b0000000000011010 #
#550
0%
#551
b0000000000010000 #
1%
#552
0%
#553
1%
b0000000000000110 #
#554
0%
#555
1%
b0000000000000100 &
b0000000000000100 !
#556
0%
#557
b0000000000000010 #
1%
#558
0%
#559
b0000000000000010 &
1%
b0000000000000010 !
#560
0%
#561
1%
b0000000000000000 #
1"
#562
0%
1)
b0000000000001101 '
b0000000000000001 $
#563
1%
b0000000000001101 &
0"
b0000000000001101 !
b0000000000000001 #
#564
0)
0%
#565
1%
b0000000000001100 !
b0000000000001100 &
#566
0%
#567
1%
b0000000000001011 &
b0000000000001011 !
#568
0%
#569
b0000000000001010 !
b0000000000001010 &
1%
#570
0%
#571
1%
b0000000000001001 &
b0000000000001001 !
#572
0%
#573
1%
b0000000000001000 !
b0000000000001000 &
#574
0%
#575
b0000000000000111 !
1%
b0000000000000111 &
#576
0%
#577
b0000000000000110 !
1%
b0000000000000110 &
#578
0%
#579
1%
b0000000000000101 &
b0000000000000101 !
#580
0%
#581
1%
b0000000000000100 &
b0000000000000100 !
#582
0%
#583
1%
b0000000000000011 &
b0000000000000011 !
#584
0%
#585
b0000000000000010 &
1%
b0000000000000010 !
#586
0%
#587
1%
b0000000000000001 !
b0000000000000001 &
#588
0%
#589
1%
b0000000000000000 #
1"
#590
b0000000000001000 $
0%
1)
#591
1%
b0000000000001101 &
0"
b0000000000001101 !
b0000000000001000 #
#592
0)
0%
#593
1%
b0000000000000101 &
b0000000000000101 !
#594
0%
#595
1%
b0000000000000011 #
#596
0%
#597
b0000000000000010 &
1%
b0000000000000010 !
#598
0%
#599
1%
b0000000000000001 #
#600
0%
#601
1%
b0000000000000001 !
b0000000000000001 &
#602
0%
#603
1%
b0000000000000000 #
1"
#604
b0000000000001111 $
0%
1)
#605
1%
b0000000000001101 &
0"
b0000000000001101 !
b0000000000001111 #
#606
0)
0%
#607
b0000000000000010 #
1%
#608
0%
#609
1%
b0000000000001011 &
b0000000000001011 !
#610
0%
#611
1%
b0000000000001001 &
b0000000000001001 !
#612
0%
#613
b0000000000000111 !
1%
b0000000000000111 &
#614
0%
#615
1%
b0000000000000101 &
b0000000000000101 !
#616
0%
#617
1%
b0000000000000011 &
b0000000000000011 !
#618
0%
#619
1%
b0000000000000001 !
b0000000000000001 &
#620
0%
#621
1%
b0000000000000001 #
#622
0%
#623
1%
b0000000000000000 #
1"
#624
b0000000000010110 $
0%
1)
#625
b0000000000010110 #
1%
b0000000000001101 &
0"
b0000000000001101 !
#626
0)
0%
#627
b0000000000001001 #
1%
#628
0%
#629
1%
b0000000000000100 &
b0000000000000100 !
#630
0%
#631
b0000000000000101 #
1%
#632
0%
#633
1%
b0000000000000001 #
#634
0%
#635
1%
b0000000000000011 &
b0000000000000011 !
#636
0%
#637
b0000000000000010 &
1%
b0000000000000010 !
#638
0%
#639
1%
b0000000000000001 !
b0000000000000001 &
#640
0%
#641
1%
b0000000000000000 #
1"
#642
0%
b0000000000011101 $
1)
#643
b0000000000011101 #
1%
b0000000000001101 &
0"
b0000000000001101 !
#644
0)
0%
#645
b0000000000010000 #
1%
#646
0%
#647
1%
b0000000000000011 #
#648
0%
#649
b0000000000001010 !
b0000000000001010 &
1%
#650
0%
#651
b0000000000000111 !
1%
b0000000000000111 &
#652
0%
#653
1%
b0000000000000100 &
b0000000000000100 !
#654
0%
#655
1%
b0000000000000001 !
b0000000000000001 &
#656
0%
#657
b0000000000000010 #
1%
#658
0%
#659
1%
b0000000000000001 #
#660
0%
#661
1%
b0000000000000000 #
1"
#662
0%
1)
b0000000000100100 $
#663
1%
b0000000000001101 &
0"
b0000000000001101 !
b0000000000100100 #
#664
0)
0%
#665
1%
b0000000000010111 #
#666
0%
#667
1%
b0000000000001010 #
#668
0%
#669
1%
b0000000000000011 &
b0000000000000011 !
#670
0%
#671
1%
b0000000000000111 #
#672
0%
#673
b0000000000000100 #
1%
#674
0%
#675
1%
b0000000000000001 #
#676
0%
#677
b0000000000000010 &
1%
b0000000000000010 !
#678
0%
#679
1%
b0000000000000001 !
b0000000000000001 &
#680
0%
#681
1%
b0000000000000000 #
1"
#682
b0000000000010000 '
0%
1)
b0000000000000001 $
#683
b0000000000010000 &
1%
b0000000000010000 !
0"
b0000000000000001 #
#684
0)
0%
#685
b0000000000001111 &
1%
b0000000000001111 !
#686
0%
#687
b0000000000001110 &
b0000000000001110 !
1%
#688
0%
#689
1%
b0000000000001101 &
b0000000000001101 !
#690
0%
#691
1%
b0000000000001100 !
b0000000000001100 &
#692
0%
#693
1%
b0000000000001011 &
b0000000000001011 !
#694
0%
#695
b0000000000001010 !
b0000000000001010 &
1%
#696
0%
#697
1%
b0000000000001001 &
b0000000000001001 !
#698
0%
#699
1%
b0000000000001000 !
b0000000000001000 &
#700
0%
#701
b0000000000000111 !
1%
b0000000000000111 &
#702
0%
#703
b0000000000000110 !
1%
b0000000000000110 &
#704
0%
#705
1%
b0000000000000101 &
b0000000000000101 !
#706
0%
#707
1%
b0000000000000100 &
b0000000000000100 !
#708
0%
#709
1%
b0000000000000011 &
b0000000000000011 !
#710
0%
#711
b0000000000000010 &
1%
b0000000000000010 !
#712
0%
#713
1%
b0000000000000001 !
b0000000000000001 &
#714
0%
#715
1%
b0000000000000000 #
1"
#716
b0000000000001000 $
0%
1)
#717
b0000000000010000 &
1%
b0000000000010000 !
0"
b0000000000001000 #
#718
0)
0%
#719
1%
b0000000000001000 !
b0000000000001000 &
#720
0%
#721
1%
b0000000000000000 #
1"
#722
b0000000000001111 $
0%
1)
#723
b0000000000010000 &
1%
b0000000000010000 !
0"
b0000000000001111 #
#724
0)
0%
#725
1%
b0000000000000001 !
b0000000000000001 &
#726
0%
#727
b0000000000001110 #
1%
#728
0%
#729
1%
b0000000000001101 #
#730
0%
#731
1%
b0000000000001100 #
#732
0%
#733
1%
b0000000000001011 #
#734
0%
#735
1%
b0000000000001010 #
#736
0%
#737
b0000000000001001 #
1%
#738
0%
#739
1%
b0000000000001000 #
#740
0%
#741
1%
b0000000000000111 #
#742
0%
#743
1%
b0000000000000110 #
#744
0%
#745
b0000000000000101 #
1%
#746
0%
#747
b0000000000000100 #
1%
#748
0%
#749
1%
b0000000000000011 #
#750
0%
#751
b0000000000000010 #
1%
#752
0%
#753
1%
b0000000000000001 #
#754
0%
#755
1%
b0000000000000000 #
1"
#756
b0000000000010110 $
0%
1)
#757
b0000000000010110 #
b0000000000010000 &
1%
b0000000000010000 !
0"
#758
0)
0%
#759
1%
b0000000000000110 #
#760
0%
#761
b0000000000001010 !
b0000000000001010 &
1%
#762
0%
#763
1%
b0000000000000100 &
b0000000000000100 !
#764
0%
#765
b0000000000000010 #
1%
#766
0%
#767
b0000000000000010 &
1%
b0000000000000010 !
#768
0%
#769
1%
b0000000000000000 #
1"
#770
0%
b0000000000011101 $
1)
#771
b0000000000010000 &
b0000000000011101 #
1%
b0000000000010000 !
0"
#772
0)
0%
#773
1%
b0000000000001101 #
#774
0%
#775
1%
b0000000000000011 &
b0000000000000011 !
#776
0%
#777
1%
b0000000000001010 #
#778
0%
#779
1%
b0000000000000111 #
#780
0%
#781
b0000000000000100 #
1%
#782
0%
#783
1%
b0000000000000001 #
#784
0%
#785
b0000000000000010 &
1%
b0000000000000010 !
#786
0%
#787
1%
b0000000000000001 !
b0000000000000001 &
#788
0%
#789
1%
b0000000000000000 #
1"
#790
0%
1)
b0000000000100100 $
#791
b0000000000010000 &
1%
b0000000000010000 !
0"
b0000000000100100 #
#792
0)
0%
#793
1%
b0000000000010100 #
#794
0%
#795
b0000000000000100 #
1%
#796
0%
#797
1%
b0000000000001100 !
b0000000000001100 &
#798
0%
#799
1%
b0000000000001000 !
b0000000000001000 &
#800
0%
#801
1%
b0000000000000100 &
b0000000000000100 !
#802
0%
#803
1%
b0000000000000000 #
1"
#804
0%
b0000000000010011 '
1)
b0000000000000001 $
#805
1%
0"
b0000000000010011 !
b0000000000000001 #
b0000000000010011 &
#806
0)
0%
#807
1%
b0000000000010010 &
b0000000000010010 !
#808
0%
#809
b0000000000010001 !
1%
b0000000000010001 &
#810
0%
#811
b0000000000010000 &
1%
b0000000000010000 !
#812
0%
#813
b0000000000001111 &
1%
b0000000000001111 !
#814
0%
#815
b0000000000001110 &
b0000000000001110 !
1%
#816
0%
#817
1%
b0000000000001101 &
b0000000000001101 !
#818
0%
#819
1%
b0000000000001100 !
b0000000000001100 &
#820
0%
#821
1%
b0000000000001011 &
b0000000000001011 !
#822
0%
#823
b0000000000001010 !
b0000000000001010 &
1%
#824
0%
#825
1%
b0000000000001001 &
b0000000000001001 !
#826
0%
#827
1%
b0000000000001000 !
b0000000000001000 &
#828
0%
#829
b0000000000000111 !
1%
b0000000000000111 &
#830
0%
#831
b0000000000000110 !
1%
b0000000000000110 &
#832
0%
#833
1%
b0000000000000101 &
b0000000000000101 !
#834
0%
#835
1%
b0000000000000100 &
b0000000000000100 !
#836
0%
#837
1%
b0000000000000011 &
b0000000000000011 !
#838
0%
#839
b0000000000000010 &
1%
b0000000000000010 !
#840
0%
#841
1%
b0000000000000001 !
b0000000000000001 &
#842
0%
#843
1%
b0000000000000000 #
1"
#844
b0000000000001000 $
0%
1)
#845
1%
0"
b0000000000010011 !
b0000000000001000 #
b0000000000010011 &
#846
0)
0%
#847
1%
b0000000000001011 &
b0000000000001011 !
#848
0%
#849
1%
b0000000000000011 &
b0000000000000011 !
#850
0%
#851
b0000000000000101 #
1%
#852
0%
#853
b0000000000000010 #
1%
#854
0%
#855
1%
b0000000000000001 !
b0000000000000001 &
#856
0%
#857
1%
b0000000000000001 #
#858
0%
#859
1%
b0000000000000000 #
1"
#860
b0000000000001111 $
0%
1)
#861
1%
0"
b0000000000010011 !
b0000000000001111 #
b0000000000010011 &
#862
0)
0%
#863
1%
b0000000000000100 &
b0000000000000100 !
#864
0%
#865
1%
b0000000000001011 #
#866
0%
#867
1%
b0000000000000111 #
#868
0%
#869
1%
b0000000000000011 #
#870
0%
#871
1%
b0000000000000001 !
b0000000000000001 &
#872
0%
#873
b0000000000000010 #
1%
#874
0%
#875
1%
b0000000000000001 #
#876
0%
#877
1%
b0000000000000000 #
1"
#878
b0000000000010110 $
0%
1)
#879
b0000000000010110 #
1%
0"
b0000000000010011 !
b0000000000010011 &
#880
0)
0%
#881
1%
b0000000000000011 #
#882
0%
#883
b0000000000010000 &
1%
b0000000000010000 !
#884
0%
#885
1%
b0000000000001101 &
b0000000000001101 !
#886
0%
#887
b0000000000001010 !
b0000000000001010 &
1%
#888
0%
#889
b0000000000000111 !
1%
b0000000000000111 &
#890
0%
#891
1%
b0000000000000100 &
b0000000000000100 !
#892
0%
#893
1%
b0000000000000001 !
b0000000000000001 &
#894
0%
#895
b0000000000000010 #
1%
#896
0%
#897
1%
b0000000000000001 #
#898
0%
#899
1%
b0000000000000000 #
1"
#900
0%
b0000000000011101 $
1)
#901
b0000000000011101 #
1%
0"
b0000000000010011 !
b0000000000010011 &
#902
0)
0%
#903
1%
b0000000000001010 #
#904
0%
#905
1%
b0000000000001001 &
b0000000000001001 !
#906
0%
#907
1%
b0000000000000001 #
#908
0%
