examples/example-chisel3/test_run_dir/gcd.GCDTester906586546/GCD.v
`ifdef RANDOMIZE_GARBAGE_ASSIGN
`define RANDOMIZE
`endif
`ifdef RANDOMIZE_INVALID_ASSIGN
`define RANDOMIZE
`endif
`ifdef RANDOMIZE_REG_INIT
`define RANDOMIZE
`endif
`ifdef RANDOMIZE_MEM_INIT
`define RANDOMIZE
`endif

module GCD(
  input         clock,
  input         reset,
  input  [15:0] io_value1,
  input  [15:0] io_value2,
  input         io_loadingValues,
  output [15:0] io_outputGCD,
  output        io_outputValid
);
  reg [15:0] x; // @[GCD.scala 21:15]
  reg [31:0] _RAND_0;
  reg [15:0] y; // @[GCD.scala 22:15]
  reg [31:0] _RAND_1;
  wire  _T_9; // @[GCD.scala 24:10]
  wire [16:0] _T_10; // @[GCD.scala 24:24]
  wire [16:0] _T_11; // @[GCD.scala 24:24]
  wire [15:0] _T_12; // @[GCD.scala 24:24]
  wire [16:0] _T_13; // @[GCD.scala 25:25]
  wire [16:0] _T_14; // @[GCD.scala 25:25]
  wire [15:0] _T_15; // @[GCD.scala 25:25]
  wire [15:0] _GEN_0; // @[GCD.scala 24:15]
  wire [15:0] _GEN_1; // @[GCD.scala 24:15]
  wire [15:0] _GEN_2; // @[GCD.scala 27:26]
  wire [15:0] _GEN_3; // @[GCD.scala 27:26]
  wire  _T_17; // @[GCD.scala 33:23]
  assign _T_9 = x > y; // @[GCD.scala 24:10]
  assign _T_10 = x - y; // @[GCD.scala 24:24]
  assign _T_11 = $unsigned(_T_10); // @[GCD.scala 24:24]
  assign _T_12 = _T_11[15:0]; // @[GCD.scala 24:24]
  assign _T_13 = y - x; // @[GCD.scala 25:25]
  assign _T_14 = $unsigned(_T_13); // @[GCD.scala 25:25]
  assign _T_15 = _T_14[15:0]; // @[GCD.scala 25:25]
  assign _GEN_0 = _T_9 ? _T_12 : x; // @[GCD.scala 24:15]
  assign _GEN_1 = _T_9 ? y : _T_15; // @[GCD.scala 24:15]
  assign _GEN_2 = io_loadingValues ? io_value1 : _GEN_0; // @[GCD.scala 27:26]
  assign _GEN_3 = io_loadingValues ? io_value2 : _GEN_1; // @[GCD.scala 27:26]
  assign _T_17 = y == 16'h0; // @[GCD.scala 33:23]
  assign io_outputGCD = x;
  assign io_outputValid = _T_17;
`ifdef RANDOMIZE
  integer initvar;
  initial begin
    `ifndef verilator
      #0.002 begin end
    `endif
  `ifdef RANDOMIZE_REG_INIT
  _RAND_0 = {1{$random}};
  x = _RAND_0[15:0];
  `endif // RANDOMIZE_REG_INIT
  `ifdef RANDOMIZE_REG_INIT
  _RAND_1 = {1{$random}};
  y = _RAND_1[15:0];
  `endif // RANDOMIZE_REG_INIT
  end
`endif // RANDOMIZE
  always @(posedge clock) begin
    if (io_loadingValues) begin
      x <= io_value1;
    end else begin
      if (_T_9) begin
        x <= _T_12;
      end
    end
    if (io_loadingValues) begin
      y <= io_value2;
    end else begin
      if (!(_T_9)) begin
        y <= _T_15;
      end
    end
  end
endmodule

examples/example-chisel3/test_run_dir/gcd.GCDTester1810643262/GCD.vcd
$version Generated by VerilatedVcd $end
$date Wed Jul 11 15:00:13 2018
 $end
$timescale   1ns $end

 $scope module TOP $end
  $var wire  1 % clock $end
  $var wire  1 ) io_loadingValues $end
  $var wire 16 * io_outputGCD [15:0] $end
  $var wire  1 + io_outputValid $end
  $var wire 16 ' io_value1 [15:0] $end
  $var wire 16 ( io_value2 [15:0] $end
  $var wire  1 & reset $end
  $scope module GCD $end
   $var wire  1 % clock $end
   $var wire  1 ) io_loadingValues $end
   $var wire 16 * io_outputGCD [15:0] $end
   $var wire  1 + io_outputValid $end
   $var wire 16 ' io_value1 [15:0] $end
   $var wire 16 ( io_value2 [15:0] $end
   $var wire  1 & reset $end
   $var wire 16 # x [15:0] $end
   $var wire 16 $ y [15:0] $end
  $upscope $end
 $upscope $end
$enddefinitions $end


#0
b0000000000000000 #
b0000000000000000 $
0%
1&
b0000000000000000 '
b0000000000000000 (
0)
b0000000000000000 *
1+
#1
1%
#2
0%
#3
1%
#4
0%
#5
1%
#6
0%
#7
1%
#8
0%
#9
1%
#10
0%
0&
b0000000000000001 '
b0000000000000001 (
1)
#11
b0000000000000001 #
b0000000000000001 $
1%
b0000000000000001 *
0+
#12
0%
0)
#13
b0000000000000000 $
1%
1+
#14
0%
b0000000000001000 (
1)
#15
b0000000000001000 $
1%
0+
#16
0%
0)
#17
b0000000000000111 $
1%
#18
0%
#19
b0000000000000110 $
1%
#20
0%
#21
b0000000000000101 $
1%
#22
0%
#23
b0000000000000100 $
1%
#24
0%
#25
b0000000000000011 $
1%
#26
0%
#27
b0000000000000010 $
1%
#28
0%
#29
b0000000000000001 $
1%
#30
0%
#31
b0000000000000000 $
1%
1+
#32
0%
b0000000000001111 (
1)
#33
b0000000000001111 $
1%
0+
#34
0%
0)
#35
b0000000000001110 $
1%
#36
0%
#37
b0000000000001101 $
1%
#38
0%
#39
b0000000000001100 $
1%
#40
0%
#41
b0000000000001011 $
1%
#42
0%
#43
b0000000000001010 $
1%
#44
0%
#45
b0000000000001001 $
1%
#46
0%
#47
b0000000000001000 $
1%
#48
0%
#49
b0000000000000111 $
1%
#50
0%
#51
b0000000000000110 $
1%
#52
0%
#53
b0000000000000101 $
1%
#54
0%
#55
b0000000000000100 $
1%
#56
0%
#57
b0000000000000011 $
1%
#58
0%
#59
b0000000000000010 $
1%
#60
0%
#61
b0000000000000001 $
1%
#62
0%
#63
b0000000000000000 $
1%
1+
#64
0%
b0000000000010110 (
1)
#65
b0000000000010110 $
1%
0+
#66
0%
0)
#67
b0000000000010101 $
1%
#68
0%
#69
b0000000000010100 $
1%
#70
0%
#71
b0000000000010011 $
1%
#72
0%
#73
b0000000000010010 $
1%
#74
0%
#75
b0000000000010001 $
1%
#76
0%
#77
b0000000000010000 $
1%
#78
0%
#79
b0000000000001111 $
1%
#80
0%
#81
b0000000000001110 $
1%
#82
0%
#83
b0000000000001101 $
1%
#84
0%
#85
b0000000000001100 $
1%
#86
0%
#87
b0000000000001011 $
1%
#88
0%
#89
b0000000000001010 $
1%
#90
0%
#91
b0000000000001001 $
1%
#92
0%
#93
b0000000000001000 $
1%
#94
0%
#95
b0000000000000111 $
1%
#96
0%
#97
b0000000000000110 $
1%
#98
0%
#99
b0000000000000101 $
1%
#100
0%
#101
b0000000000000100 $
1%
#102
0%
#103
b0000000000000011 $
1%
#104
0%
#105
b0000000000000010 $
1%
#106
0%
#107
b0000000000000001 $
1%
#108
0%
#109
b0000000000000000 $
1%
1+
#110
0%
b0000000000011101 (
1)
#111
b0000000000011101 $
1%
0+
#112
0%
0)
#113
b0000000000011100 $
1%
#114
0%
#115
b0000000000011011 $
1%
#116
0%
#117
b0000000000011010 $
1%
#118
0%
#119
b0000000000011001 $
1%
#120
0%
#121
b0000000000011000 $
1%
#122
0%
#123
b0000000000010111 $
1%
#124
0%
#125
b0000000000010110 $
1%
#126
0%
#127
b0000000000010101 $
1%
#128
0%
#129
b0000000000010100 $
1%
#130
0%
#131
b0000000000010011 $
1%
#132
0%
#133
b0000000000010010 $
1%
#134
0%
#135
b0000000000010001 $
1%
#136
0%
#137
b0000000000010000 $
1%
#138
0%
#139
b0000000000001111 $
1%
#140
0%
#141
b0000000000001110 $
1%
#142
0%
#143
b0000000000001101 $
1%
#144
0%
#145
b0000000000001100 $
1%
#146
0%
#147
b0000000000001011 $
1%
#148
0%
#149
b0000000000001010 $
1%
#150
0%
#151
b0000000000001001 $
1%
#152
0%
#153
b0000000000001000 $
1%
#154
0%
#155
b0000000000000111 $
1%
#156
0%
#157
b0000000000000110 $
1%
#158
0%
#159
b0000000000000101 $
1%
#160
0%
#161
b0000000000000100 $
1%
#162
0%
#163
b0000000000000011 $
1%
#164
0%
#165
b0000000000000010 $
1%
#166
0%
#167
b0000000000000001 $
1%
#168
0%
#169
b0000000000000000 $
1%
1+
#170
0%
b0000000000100100 (
1)
#171
b0000000000100100 $
1%
0+
#172
0%
0)
#173
b0000000000100011 $
1%
#174
0%
#175
b0000000000100010 $
1%
#176
0%
#177
b0000000000100001 $
1%
#178
0%
#179
b0000000000100000 $
1%
#180
0%
#181
b0000000000011111 $
1%
#182
0%
#183
b0000000000011110 $
1%
#184
0%
#185
b0000000000011101 $
1%
#186
0%
#187
b0000000000011100 $
1%
#188
0%
#189
b0000000000011011 $
1%
#190
0%
#191
b0000000000011010 $
1%
#192
0%
#193
b0000000000011001 $
1%
#194
0%
#195
b0000000000011000 $
1%
#196
0%
#197
b0000000000010111 $
1%
#198
0%
#199
b0000000000010110 $
1%
#200
0%
#201
b0000000000010101 $
1%
#202
0%
#203
b0000000000010100 $
1%
#204
0%
#205
b0000000000010011 $
1%
#206
0%
#207
b0000000000010010 $
1%
#208
0%
#209
b0000000000010001 $
1%
#210
0%
#211
b0000000000010000 $
1%
#212
0%
#213
b0000000000001111 $
1%
#214
0%
#215
b0000000000001110 $
1%
#216
0%
#217
b0000000000001101 $
1%
#218
0%
#219
b0000000000001100 $
1%
#220
0%
#221
b0000000000001011 $
1%
#222
0%
#223
b0000000000001010 $
1%
#224
0%
#225
b0000000000001001 $
1%
#226
0%
#227
b0000000000001000 $
1%
#228
0%
#229
b0000000000000111 $
1%
#230
0%
#231
b0000000000000110 $
1%
#232
0%
#233
b0000000000000101 $
1%
#234
0%
#235
b0000000000000100 $
1%
#236
0%
#237
b0000000000000011 $
1%
#238
0%
#239
b0000000000000010 $
1%
#240
0%
#241
b0000000000000001 $
1%
#242
0%
#243
b0000000000000000 $
1%
1+
#244
0%
b0000000000000100 '
b0000000000000001 (
1)
#245
b0000000000000100 #
b0000000000000001 $
1%
b0000000000000100 *
0+
#246
0%
0)
#247
b0000000000000011 #
1%
b0000000000000011 *
#248
0%
#249
b0000000000000010 #
1%
b0000000000000010 *
#250
0%
#251
b0000000000000001 #
1%
b0000000000000001 *
#252
0%
#253
b0000000000000000 $
1%
1+
#254
0%
b0000000000001000 (
1)
#255
b0000000000000100 #
b0000000000001000 $
1%
b0000000000000100 *
0+
#256
0%
0)
#257
b0000000000000100 $
1%
#258
0%
#259
b0000000000000000 $
1%
1+
#260
0%
b0000000000001111 (
1)
#261
b0000000000001111 $
1%
0+
#262
0%
0)
#263
b0000000000001011 $
1%
#264
0%
#265
b0000000000000111 $
1%
#266
0%
#267
b0000000000000011 $
1%
#268
0%
#269
b0000000000000001 #
1%
b0000000000000001 *
#270
0%
#271
b0000000000000010 $
1%
#272
0%
#273
b0000000000000001 $
1%
#274
0%
#275
b0000000000000000 $
1%
1+
#276
0%
b0000000000010110 (
1)
#277
b0000000000000100 #
b0000000000010110 $
1%
b0000000000000100 *
0+
#278
0%
0)
#279
b0000000000010010 $
1%
#280
0%
#281
b0000000000001110 $
1%
#282
0%
#283
b0000000000001010 $
1%
#284
0%
#285
b0000000000000110 $
1%
#286
0%
#287
b0000000000000010 $
1%
#288
0%
#289
b0000000000000010 #
1%
b0000000000000010 *
#290
0%
#291
b0000000000000000 $
1%
1+
#292
0%
b0000000000011101 (
1)
#293
b0000000000000100 #
b0000000000011101 $
1%
b0000000000000100 *
0+
#294
0%
0)
#295
b0000000000011001 $
1%
#296
0%
#297
b0000000000010101 $
1%
#298
0%
#299
b0000000000010001 $
1%
#300
0%
#301
b0000000000001101 $
1%
#302
0%
#303
b0000000000001001 $
1%
#304
0%
#305
b0000000000000101 $
1%
#306
0%
#307
b0000000000000001 $
1%
#308
0%
#309
b0000000000000011 #
1%
b0000000000000011 *
#310
0%
#311
b0000000000000010 #
1%
b0000000000000010 *
#312
0%
#313
b0000000000000001 #
1%
b0000000000000001 *
#314
0%
#315
b0000000000000000 $
1%
1+
#316
0%
b0000000000100100 (
1)
#317
b0000000000000100 #
b0000000000100100 $
1%
b0000000000000100 *
0+
#318
0%
0)
#319
b0000000000100000 $
1%
#320
0%
#321
b0000000000011100 $
1%
#322
0%
#323
b0000000000011000 $
1%
#324
0%
#325
b0000000000010100 $
1%
#326
0%
#327
b0000000000010000 $
1%
#328
0%
#329
b0000000000001100 $
1%
#330
0%
#331
b0000000000001000 $
1%
#332
0%
#333
b0000000000000100 $
1%
#334
0%
#335
b0000000000000000 $
1%
1+
#336
0%
b0000000000000111 '
b0000000000000001 (
1)
#337
b0000000000000111 #
b0000000000000001 $
1%
b0000000000000111 *
0+
#338
0%
0)
#339
b0000000000000110 #
1%
b0000000000000110 *
#340
0%
#341
b0000000000000101 #
1%
b0000000000000101 *
#342
0%
#343
b0000000000000100 #
1%
b0000000000000100 *
#344
0%
#345
b0000000000000011 #
1%
b0000000000000011 *
#346
0%
#347
b0000000000000010 #
1%
b0000000000000010 *
#348
0%
#349
b0000000000000001 #
1%
b0000000000000001 *
#350
0%
#351
b0000000000000000 $
1%
1+
#352
0%
b0000000000001000 (
1)
#353
b0000000000000111 #
b0000000000001000 $
1%
b0000000000000111 *
0+
#354
0%
0)
#355
b0000000000000001 $
1%
#356
0%
#357
b0000000000000110 #
1%
b0000000000000110 *
#358
0%
#359
b0000000000000101 #
1%
b0000000000000101 *
#360
0%
#361
b0000000000000100 #
1%
b0000000000000100 *
#362
0%
#363
b0000000000000011 #
1%
b0000000000000011 *
#364
0%
#365
b0000000000000010 #
1%
b0000000000000010 *
#366
0%
#367
b0000000000000001 #
1%
b0000000000000001 *
#368
0%
#369
b0000000000000000 $
1%
1+
#370
0%
b0000000000001111 (
1)
#371
b0000000000000111 #
b0000000000001111 $
1%
b0000000000000111 *
0+
#372
0%
0)
#373
b0000000000001000 $
1%
#374
0%
#375
b0000000000000001 $
1%
#376
0%
#377
b0000000000000110 #
1%
b0000000000000110 *
#378
0%
#379
b0000000000000101 #
1%
b0000000000000101 *
#380
0%
#381
b0000000000000100 #
1%
b0000000000000100 *
#382
0%
#383
b0000000000000011 #
1%
b0000000000000011 *
#384
0%
#385
b0000000000000010 #
1%
b0000000000000010 *
#386
0%
#387
b0000000000000001 #
1%
b0000000000000001 *
#388
0%
#389
b0000000000000000 $
1%
1+
#390
0%
b0000000000010110 (
1)
#391
b0000000000000111 #
b0000000000010110 $
1%
b0000000000000111 *
0+
#392
0%
0)
#393
b0000000000001111 $
1%
#394
0%
#395
b0000000000001000 $
1%
#396
0%
#397
b0000000000000001 $
1%
#398
0%
#399
b0000000000000110 #
1%
b0000000000000110 *
#400
0%
#401
b0000000000000101 #
1%
b0000000000000101 *
#402
0%
#403
b0000000000000100 #
1%
b0000000000000100 *
#404
0%
#405
b0000000000000011 #
1%
b0000000000000011 *
#406
0%
#407
b0000000000000010 #
1%
b0000000000000010 *
#408
0%
#409
b0000000000000001 #
1%
b0000000000000001 *
#410
0%
#411
b0000000000000000 $
1%
1+
#412
0%
b0000000000011101 (
1)
#413
b0000000000000111 #
b0000000000011101 $
1%
b0000000000000111 *
0+
#414
0%
0)
#415
b0000000000010110 $
1%
#416
0%
#417
b0000000000001111 $
1%
#418
0%
#419
b0000000000001000 $
1%
#420
0%
#421
b0000000000000001 $
1%
#422
0%
#423
b0000000000000110 #
1%
b0000000000000110 *
#424
0%
#425
b0000000000000101 #
1%
b0000000000000101 *
#426
0%
#427
b0000000000000100 #
1%
b0000000000000100 *
#428
0%
#429
b0000000000000011 #
1%
b0000000000000011 *
#430
0%
#431
b0000000000000010 #
1%
b0000000000000010 *
#432
0%
#433
b0000000000000001 #
1%
b0000000000000001 *
#434
0%
#435
b0000000000000000 $
1%
1+
#436
0%
b0000000000100100 (
1)
#437
b0000000000000111 #
b0000000000100100 $
1%
b0000000000000111 *
0+
#438
0%
0)
#439
b0000000000011101 $
1%
#440
0%
#441
b0000000000010110 $
1%
#442
0%
#443
b0000000000001111 $
1%
#444
0%
#445
b0000000000001000 $
1%
#446
0%
#447
b0000000000000001 $
1%
#448
0%
#449
b0000000000000110 #
1%
b0000000000000110 *
#450
0%
#451
b0000000000000101 #
1%
b0000000000000101 *
#452
0%
#453
b0000000000000100 #
1%
b0000000000000100 *
#454
0%
#455
b0000000000000011 #
1%
b0000000000000011 *
#456
0%
#457
b0000000000000010 #
1%
b0000000000000010 *
#458
0%
#459
b0000000000000001 #
1%
b0000000000000001 *
#460
0%
#461
b0000000000000000 $
1%
1+
#462
0%
b0000000000001010 '
b0000000000000001 (
1)
#463
b0000000000001010 #
b0000000000000001 $
1%
b0000000000001010 *
0+
#464
0%
0)
#465
b0000000000001001 #
1%
b0000000000001001 *
#466
0%
#467
b0000000000001000 #
1%
b0000000000001000 *
#468
0%
#469
b0000000000000111 #
1%
b0000000000000111 *
#470
0%
#471
b0000000000000110 #
1%
b0000000000000110 *
#472
0%
#473
b0000000000000101 #
1%
b0000000000000101 *
#474
0%
#475
b0000000000000100 #
1%
b0000000000000100 *
#476
0%
#477
b0000000000000011 #
1%
b0000000000000011 *
#478
0%
#479
b0000000000000010 #
1%
b0000000000000010 *
#480
0%
#481
b0000000000000001 #
1%
b0000000000000001 *
#482
0%
#483
b0000000000000000 $
1%
1+
#484
0%
b0000000000001000 (
1)
#485
b0000000000001010 #
b0000000000001000 $
1%
b0000000000001010 *
0+
#486
0%
0)
#487
b0000000000000010 #
1%
b0000000000000010 *
#488
0%
#489
b0000000000000110 $
1%
#490
0%
#491
b0000000000000100 $
1%
#492
0%
#493
b0000000000000010 $
1%
#494
0%
#495
b0000000000000000 $
1%
1+
#496
0%
b0000000000001111 (
1)
#497
b0000000000001010 #
b0000000000001111 $
1%
b0000000000001010 *
0+
#498
0%
0)
#499
b0000000000000101 $
1%
#500
0%
#501
b0000000000000101 #
1%
b0000000000000101 *
#502
0%
#503
b0000000000000000 $
1%
1+
#504
0%
b0000000000010110 (
1)
#505
b0000000000001010 #
b0000000000010110 $
1%
b0000000000001010 *
0+
#506
0%
0)
#507
b0000000000001100 $
1%
#508
0%
#509
b0000000000000010 $
1%
#510
0%
#511
b0000000000001000 #
1%
b0000000000001000 *
#512
0%
#513
b0000000000000110 #
1%
b0000000000000110 *
#514
0%
#515
b0000000000000100 #
1%
b0000000000000100 *
#516
0%
#517
b0000000000000010 #
1%
b0000000000000010 *
#518
0%
#519
b0000000000000000 $
1%
1+
#520
0%
b0000000000011101 (
1)
#521
b0000000000001010 #
b0000000000011101 $
1%
b0000000000001010 *
0+
#522
0%
0)
#523
b0000000000010011 $
1%
#524
0%
#525
b0000000000001001 $
1%
#526
0%
#527
b0000000000000001 #
1%
b0000000000000001 *
#528
0%
#529
b0000000000001000 $
1%
#530
0%
#531
b0000000000000111 $
1%
#532
0%
#533
b0000000000000110 $
1%
#534
0%
#535
b0000000000000101 $
1%
#536
0%
#537
b0000000000000100 $
1%
#538
0%
#539
b0000000000000011 $
1%
#540
0%
#541
b0000000000000010 $
1%
#542
0%
#543
b0000000000000001 $
1%
#544
0%
#545
b0000000000000000 $
1%
1+
#546
0%
b0000000000100100 (
1)
#547
b0000000000001010 #
b0000000000100100 $
1%
b0000000000001010 *
0+
#548
0%
0)
#549
b0000000000011010 $
1%
#550
0%
#551
b0000000000010000 $
1%
#552
0%
#553
b0000000000000110 $
1%
#554
0%
#555
b0000000000000100 #
1%
b0000000000000100 *
#556
0%
#557
b0000000000000010 $
1%
#558
0%
#559
b0000000000000010 #
1%
b0000000000000010 *
#560
0%
#561
b0000000000000000 $
1%
1+
#562
0%
b0000000000001101 '
b0000000000000001 (
1)
#563
b0000000000001101 #
b0000000000000001 $
1%
b0000000000001101 *
0+
#564
0%
0)
#565
b0000000000001100 #
1%
b0000000000001100 *
#566
0%
#567
b0000000000001011 #
1%
b0000000000001011 *
#568
0%
#569
b0000000000001010 #
1%
b0000000000001010 *
#570
0%
#571
b0000000000001001 #
1%
b0000000000001001 *
#572
0%
#573
b0000000000001000 #
1%
b0000000000001000 *
#574
0%
#575
b0000000000000111 #
1%
b0000000000000111 *
#576
0%
#577
b0000000000000110 #
1%
b0000000000000110 *
#578
0%
#579
b0000000000000101 #
1%
b0000000000000101 *
#580
0%
#581
b0000000000000100 #
1%
b0000000000000100 *
#582
0%
#583
b0000000000000011 #
1%
b0000000000000011 *
#584
0%
#585
b0000000000000010 #
1%
b0000000000000010 *
#586
0%
#587
b0000000000000001 #
1%
b0000000000000001 *
#588
0%
#589
b0000000000000000 $
1%
1+
#590
0%
b0000000000001000 (
1)
#591
b0000000000001101 #
b0000000000001000 $
1%
b0000000000001101 *
0+
#592
0%
0)
#593
b0000000000000101 #
1%
b0000000000000101 *
#594
0%
#595
b0000000000000011 $
1%
#596
0%
#597
b0000000000000010 #
1%
b0000000000000010 *
#598
0%
#599
b0000000000000001 $
1%
#600
0%
#601
b0000000000000001 #
1%
b0000000000000001 *
#602
0%
#603
b0000000000000000 $
1%
1+
#604
0%
b0000000000001111 (
1)
#605
b0000000000001101 #
b0000000000001111 $
1%
b0000000000001101 *
0+
#606
0%
0)
#607
b0000000000000010 $
1%
#608
0%
#609
b0000000000001011 #
1%
b0000000000001011 *
#610
0%
#611
b0000000000001001 #
1%
b0000000000001001 *
#612
0%
#613
b0000000000000111 #
1%
b0000000000000111 *
#614
0%
#615
b0000000000000101 #
1%
b0000000000000101 *
#616
0%
#617
b0000000000000011 #
1%
b0000000000000011 *
#618
0%
#619
b0000000000000001 #
1%
b0000000000000001 *
#620
0%
#621
b0000000000000001 $
1%
#622
0%
#623
b0000000000000000 $
1%
1+
#624
0%
b0000000000010110 (
1)
#625
b0000000000001101 #
b0000000000010110 $
1%
b0000000000001101 *
0+
#626
0%
0)
#627
b0000000000001001 $
1%
#628
0%
#629
b0000000000000100 #
1%
b0000000000000100 *
#630
0%
#631
b0000000000000101 $
1%
#632
0%
#633
b0000000000000001 $
1%
#634
0%
#635
b0000000000000011 #
1%
b0000000000000011 *
#636
0%
#637
b0000000000000010 #
1%
b0000000000000010 *
#638
0%
#639
b0000000000000001 #
1%
b0000000000000001 *
#640
0%
#641
b0000000000000000 $
1%
1+
#642
0%
b0000000000011101 (
1)
#643
b0000000000001101 #
b0000000000011101 $
1%
b0000000000001101 *
0+
#644
0%
0)
#645
b0000000000010000 $
1%
#646
0%
#647
b0000000000000011 $
1%
#648
0%
#649
b0000000000001010 #
1%
b0000000000001010 *
#650
0%
#651
b0000000000000111 #
1%
b0000000000000111 *
#652
0%
#653
b0000000000000100 #
1%
b0000000000000100 *
#654
0%
#655
b0000000000000001 #
1%
b0000000000000001 *
#656
0%
#657
b0000000000000010 $
1%
#658
0%
#659
b0000000000000001 $
1%
#660
0%
#661
b0000000000000000 $
1%
1+
#662
0%
b0000000000100100 (
1)
#663
b0000000000001101 #
b0000000000100100 $
1%
b0000000000001101 *
0+
#664
0%
0)
#665
b0000000000010111 $
1%
#666
0%
#667
b0000000000001010 $
1%
#668
0%
#669
b0000000000000011 #
1%
b0000000000000011 *
#670
0%
#671
b0000000000000111 $
1%
#672
0%
#673
b0000000000000100 $
1%
#674
0%
#675
b0000000000000001 $
1%
#676
0%
#677
b0000000000000010 #
1%
b0000000000000010 *
#678
0%
#679
b0000000000000001 #
1%
b0000000000000001 *
#680
0%
#681
b0000000000000000 $
1%
1+
#682
0%
b0000000000010000 '
b0000000000000001 (
1)
#683
b0000000000010000 #
b0000000000000001 $
1%
b0000000000010000 *
0+
#684
0%
0)
#685
b0000000000001111 #
1%
b0000000000001111 *
#686
0%
#687
b0000000000001110 #
1%
b0000000000001110 *
#688
0%
#689
b0000000000001101 #
1%
b0000000000001101 *
#690
0%
#691
b0000000000001100 #
1%
b0000000000001100 *
#692
0%
#693
b0000000000001011 #
1%
b0000000000001011 *
#694
0%
#695
b0000000000001010 #
1%
b0000000000001010 *
#696
0%
#697
b0000000000001001 #
1%
b0000000000001001 *
#698
0%
#699
b0000000000001000 #
1%
b0000000000001000 *
#700
0%
#701
b0000000000000111 #
1%
b0000000000000111 *
#702
0%
#703
b0000000000000110 #
1%
b0000000000000110 *
#704
0%
#705
b0000000000000101 #
1%
b0000000000000101 *
#706
0%
#707
b0000000000000100 #
1%
b0000000000000100 *
#708
0%
#709
b0000000000000011 #
1%
b0000000000000011 *
#710
0%
#711
b0000000000000010 #
1%
b0000000000000010 *
#712
0%
#713
b0000000000000001 #
1%
b0000000000000001 *
#714
0%
#715
b0000000000000000 $
1%
1+
#716
0%
b0000000000001000 (
1)
#717
b0000000000010000 #
b0000000000001000 $
1%
b0000000000010000 *
0+
#718
0%
0)
#719
b0000000000001000 #
1%
b0000000000001000 *
#720
0%
#721
b0000000000000000 $
1%
1+
#722
0%
b0000000000001111 (
1)
#723
b0000000000010000 #
b0000000000001111 $
1%
b0000000000010000 *
0+
#724
0%
0)
#725
b0000000000000001 #
1%
b0000000000000001 *
#726
0%
#727
b0000000000001110 $
1%
#728
0%
#729
b0000000000001101 $
1%
#730
0%
#731
b0000000000001100 $
1%
#732
0%
#733
b0000000000001011 $
1%
#734
0%
#735
b0000000000001010 $
1%
#736
0%
#737
b0000000000001001 $
1%
#738
0%
#739
b0000000000001000 $
1%
#740
0%
#741
b0000000000000111 $
1%
#742
0%
#743
b0000000000000110 $
1%
#744
0%
#745
b0000000000000101 $
1%
#746
0%
#747
b0000000000000100 $
1%
#748
0%
#749
b0000000000000011 $
1%
#750
0%
#751
b0000000000000010 $
1%
#752
0%
#753
b0000000000000001 $
1%
#754
0%
#755
b0000000000000000 $
1%
1+
#756
0%
b0000000000010110 (
1)
#757
b0000000000010000 #
b0000000000010110 $
1%
b0000000000010000 *
0+
#758
0%
0)
#759
b0000000000000110 $
1%
#760
0%
#761
b0000000000001010 #
1%
b0000000000001010 *
#762
0%
#763
b0000000000000100 #
1%
b0000000000000100 *
#764
0%
#765
b0000000000000010 $
1%
#766
0%
#767
b0000000000000010 #
1%
b0000000000000010 *
#768
0%
#769
b0000000000000000 $
1%
1+
#770
0%
b0000000000011101 (
1)
#771
b0000000000010000 #
b0000000000011101 $
1%
b0000000000010000 *
0+
#772
0%
0)
#773
b0000000000001101 $
1%
#774
0%
#775
b0000000000000011 #
1%
b0000000000000011 *
#776
0%
#777
b0000000000001010 $
1%
#778
0%
#779
b0000000000000111 $
1%
#780
0%
#781
b0000000000000100 $
1%
#782
0%
#783
b0000000000000001 $
1%
#784
0%
#785
b0000000000000010 #
1%
b0000000000000010 *
#786
0%
#787
b0000000000000001 #
1%
b0000000000000001 *
#788
0%
#789
b0000000000000000 $
1%
1+
#790
0%
b0000000000100100 (
1)
#791
b0000000000010000 #
b0000000000100100 $
1%
b0000000000010000 *
0+
#792
0%
0)
#793
b0000000000010100 $
1%
#794
0%
#795
b0000000000000100 $
1%
#796
0%
#797
b0000000000001100 #
1%
b0000000000001100 *
#798
0%
#799
b0000000000001000 #
1%
b0000000000001000 *
#800
0%
#801
b0000000000000100 #
1%
b0000000000000100 *
#802
0%
#803
b0000000000000000 $
1%
1+
#804
0%
b0000000000010011 '
b0000000000000001 (
1)
#805
b0000000000010011 #
b0000000000000001 $
1%
b0000000000010011 *
0+
#806
0%
0)
#807
b0000000000010010 #
1%
b0000000000010010 *
#808
0%
#809
b0000000000010001 #
1%
b0000000000010001 *
#810
0%
#811
b0000000000010000 #
1%
b0000000000010000 *
#812
0%
#813
b0000000000001111 #
1%
b0000000000001111 *
#814
0%
#815
b0000000000001110 #
1%
b0000000000001110 *
#816
0%
#817
b0000000000001101 #
1%
b0000000000001101 *
#818
0%
#819
b0000000000001100 #
1%
b0000000000001100 *
#820
0%
#821
b0000000000001011 #
1%
b0000000000001011 *
#822
0%
#823
b0000000000001010 #
1%
b0000000000001010 *
#824
0%
#825
b0000000000001001 #
1%
b0000000000001001 *
#826
0%
#827
b0000000000001000 #
1%
b0000000000001000 *
#828
0%
#829
b0000000000000111 #
1%
b0000000000000111 *
#830
0%
#831
b0000000000000110 #
1%
b0000000000000110 *
#832
0%
#833
b0000000000000101 #
1%
b0000000000000101 *
#834
0%
#835
b0000000000000100 #
1%
b0000000000000100 *
#836
0%
#837
b0000000000000011 #
1%
b0000000000000011 *
#838
0%
#839
b0000000000000010 #
1%
b0000000000000010 *
#840
0%
#841
b0000000000000001 #
1%
b0000000000000001 *
#842
0%
#843
b0000000000000000 $
1%
1+
#844
0%
b0000000000001000 (
1)
#845
b0000000000010011 #
b0000000000001000 $
1%
b0000000000010011 *
0+
#846
0%
0)
#847
b0000000000001011 #
1%
b0000000000001011 *
#848
0%
#849
b0000000000000011 #
1%
b0000000000000011 *
#850
0%
#851
b0000000000000101 $
1%
#852
0%
#853
b0000000000000010 $
1%
#854
0%
#855
b0000000000000001 #
1%
b0000000000000001 *
#856
0%
#857
b0000000000000001 $
1%
#858
0%
#859
b0000000000000000 $
1%
1+
#860
0%
b0000000000001111 (
1)
#861
b0000000000010011 #
b0000000000001111 $
1%
b0000000000010011 *
0+
#862
0%
0)
#863
b0000000000000100 #
1%
b0000000000000100 *
#864
0%
#865
b0000000000001011 $
1%
#866
0%
#867
b0000000000000111 $
1%
#868
0%
#869
b0000000000000011 $
1%
#870
0%
#871
b0000000000000001 #
1%
b0000000000000001 *
#872
0%
#873
b0000000000000010 $
1%
#874
0%
#875
b0000000000000001 $
1%
#876
0%
#877
b0000000000000000 $
1%
1+
#878
0%
b0000000000010110 (
1)
#879
b0000000000010011 #
b0000000000010110 $
1%
b0000000000010011 *
0+
#880
0%
0)
#881
b0000000000000011 $
1%
#882
0%
#883
b0000000000010000 #
1%
b0000000000010000 *
#884
0%
#885
b0000000000001101 #
1%
b0000000000001101 *
#886
0%
#887
b0000000000001010 #
1%
b0000000000001010 *
#888
0%
#889
b0000000000000111 #
1%
b0000000000000111 *
#890
0%
#891
b0000000000000100 #
1%
b0000000000000100 *
#892
0%
#893
b0000000000000001 #
1%
b0000000000000001 *
#894
0%
#895
b0000000000000010 $
1%
#896
0%
#897
b0000000000000001 $
1%
#898
0%
#899
b0000000000000000 $
1%
1+
